setup.py
bwypy/__init__.py
bwypy/core.py
bwypy.egg-info/PKG-INFO
bwypy.egg-info/SOURCES.txt
bwypy.egg-info/dependency_links.txt
bwypy.egg-info/requires.txt
bwypy.egg-info/top_level.txt
bwypy/old/__init__.py
bwypy/old/bwypy.py
bwypy/old/query_builder.py